.gitignore
AUTHORS.txt
COPYING.txt
MANIFEST.in
NEWS.txt
README.txt
TODO.txt
setup.cfg
setup.py
docs/formats.txt
docs/manual.txt
examples/NC_000932.fas
examples/chloroplasts-probes-beta7.fas
vhybridize/__init__.py
vhybridize/config.py
vhybridize/locate.py
vhybridize/utils.py
vhybridize.egg-info/PKG-INFO
vhybridize.egg-info/SOURCES.txt
vhybridize.egg-info/dependency_links.txt
vhybridize.egg-info/entry_points.txt
vhybridize.egg-info/top_level.txt
vhybridize/scripts/__init__.py
vhybridize/scripts/filter.py
vhybridize/scripts/merge.py
vhybridize/scripts/split_multi_fasta.py
vhybridize/scripts/to_permutation.py
vhybridize/scripts/to_vhx.py
