Metadata-Version: 1.0
Name: vhybridize
Version: 0.5.9
Summary: virtual hybridization framework
Home-page: http://ygingras.net/bioinfo
Author: Yannick Gingras
Author-email: ygingras@ygingras.net
License: GPLv3 or later
Platform: UNKNOWN
